Metadata-Version: 2.4
Name: synbio
Version: 0.6.18
Summary: Synbio design and build library
Home-page: https://github.com/Lattice-Automation/synbio
Author: JJTimmons
Author-email: jtimmons@latticeautomation.com
License: GNU General Public License v2 (GPLv2)
Keywords: synbio,lab automation,dna assembly
Classifier: Development Status :: 3 - Alpha
Classifier: License :: OSI Approved :: GNU General Public License v2 (GPLv2)
Classifier: Operating System :: OS Independent
Classifier: Programming Language :: Python :: 3
Classifier: Topic :: Scientific/Engineering :: Bio-Informatics
Requires-Python: >=3,<3.12
License-File: LICENSE
Requires-Dist: biopython==1.77
Requires-Dist: networkx>=2.3.0
Requires-Dist: fuzzywuzzy
Requires-Dist: primers>=0.2.4
Dynamic: author
Dynamic: author-email
Dynamic: classifier
Dynamic: description
Dynamic: description-content-type
Dynamic: home-page
Dynamic: keywords
Dynamic: license
Dynamic: license-file
Dynamic: requires-dist
Dynamic: requires-python
Dynamic: summary
